Metadata-Version: 2.1
Name: honeypotshttps
Version: 0.99
Summary: 30 different honeypots in one package! (dhcp, dns, elastic, ftp, http proxy, https proxy, http, https, imap, ipp, irc, ldap, memcache, mssql, mysql, ntp, oracle, pjl, pop3, postgres, rdp, redis, sip, smb, smtp, snmp, socks5, ssh, telnet, vnc)
Home-page: https://github.com/john10909/honeypots
Author: John
Author-email: QeeqBox <gigaqeeq@gmail.com>
License: AGPL-3.0
Project-URL: Homepage, https://github.com/john10909/honeypots
Classifier: Programming Language :: Python :: 3
Classifier: License :: OSI Approved :: GNU Affero General Public License v3
Classifier: Operating System :: OS Independent
Requires-Python: >=3.8
License-File: LICENSE
Requires-Dist: impacket ==0.9.24
Requires-Dist: netifaces ==0.11.0
Requires-Dist: paramiko ==3.1.0
Requires-Dist: psutil ==5.9.0
Requires-Dist: psycopg2-binary ==2.9.3
Requires-Dist: pycryptodome ==3.19.0
Requires-Dist: requests ==2.28.2
Requires-Dist: requests[socks] ==2.28.2
Requires-Dist: scapy ==2.4.5
Requires-Dist: service-identity ==21.1.0
Requires-Dist: twisted ==21.7.0
Provides-Extra: dev
Requires-Dist: dnspython ==2.4.2 ; extra == 'dev'
Requires-Dist: elasticsearch ; extra == 'dev'
Requires-Dist: ldap3 ; extra == 'dev'
Requires-Dist: mysql-connector ; extra == 'dev'
Requires-Dist: pre-commit ; extra == 'dev'
Requires-Dist: pymssql ; extra == 'dev'
Requires-Dist: pysnmplib ; extra == 'dev'
Requires-Dist: pytest ; extra == 'dev'
Requires-Dist: redis ; extra == 'dev'
Requires-Dist: vncdotool ; extra == 'dev'
